aqua/__init__.py
aqua/core/__init__.py
aqua/core/accessor.py
aqua/core/exceptions.py
aqua/core/logger.py
aqua/core/version.py
aqua/core/analysis/__init__.py
aqua/core/analysis/analysis.py
aqua/core/analysis/cli_checker.py
aqua/core/config/config-aqua.tmpl
aqua/core/config/catgen/catalog_entry.j2
aqua/core/config/catgen/matching_grids.yaml
aqua/core/config/data_model/aqua.yaml
aqua/core/config/data_model/coords_default.yaml
aqua/core/config/fixes/EC-EARTH4.yaml
aqua/core/config/fixes/FESOM-climatedt-phase1.yaml
aqua/core/config/fixes/FESOM-default.yaml
aqua/core/config/fixes/ICON-climatedt-phase1.yaml
aqua/core/config/fixes/ICON-default.yaml
aqua/core/config/fixes/IFS-NEMO-climatedt-phase1.yaml
aqua/core/config/fixes/IFS-climatedt-phase1.yaml
aqua/core/config/fixes/IFS-nextgems.yaml
aqua/core/config/fixes/OBS-climatedt.yaml
aqua/core/config/fixes/climatedt-phase2.yaml
aqua/core/config/fixes/convention-eccodes.yaml
aqua/core/config/fixes/default.yaml
aqua/core/config/fixes/fixes.yaml.sample
aqua/core/config/fixes/tests.yaml
aqua/core/config/grids/EC-EARTH4.yaml
aqua/core/config/grids/HealPix.yaml
aqua/core/config/grids/default.yaml
aqua/core/config/grids/fesom.yaml
aqua/core/config/grids/icon.yaml
aqua/core/config/grids/ifs.yaml
aqua/core/config/grids/nemo.yaml
aqua/core/config/grids/observations.yaml
aqua/core/config/grids/tests.yaml
aqua/core/config/styles/aqua.mplstyle
aqua/core/configurer/__init__.py
aqua/core/configurer/configpath.py
aqua/core/configurer/locator.py
aqua/core/console/__init__.py
aqua/core/console/analysis.py
aqua/core/console/builder.py
aqua/core/console/catalog.py
aqua/core/console/catgen.py
aqua/core/console/drop.py
aqua/core/console/files.py
aqua/core/console/install.py
aqua/core/console/main.py
aqua/core/console/parser.py
aqua/core/console/util.py
aqua/core/data_model/__init__.py
aqua/core/data_model/coord_utils.py
aqua/core/data_model/coordidentifier.py
aqua/core/data_model/coordtransformer.py
aqua/core/data_model/datamodel.py
aqua_core-1.0.0a2.dist-info/licenses/LICENSE
aqua_core-1.0.0a2.dist-info/METADATA
aqua_core-1.0.0a2.dist-info/WHEEL
aqua_core-1.0.0a2.dist-info/entry_points.txt
aqua_core-1.0.0a2.dist-info/top_level.txt
aqua_core-1.0.0a2.dist-info/RECORD
