Metadata-Version: 2.4
Name: aqua-core
Version: 1.0.0a2
Summary: AQUA; a model evaluation framework for high-resolution climate model simulations
Author-email: Paolo Davini <paolo.davini@cnr.it>, Matteo Nurisso <m.nurisso@isac.cnr.it>, Silvia Caprioli <silvia.caprioli@polito.it>, Jost von Hardenberg <jost.hardenberg@polito.it>, Marco Cadau <marco.cadau@polito.it>, Emanuele Tovazzi <emanuele.tovazzi@cnr.it>, Supriyo Ghosh <supriyo.ghosh@bsc.es>, Maqsood Mubarak Rajput <maqsoodmubarak.rajput@awi.de>
License:                                  Apache License
Project-URL: homepage, https://github.com/DestinE-Climate-DT/AQUA/
Project-URL: documentation, https://aqua.readthedocs.io/en/latest/index.html
Project-URL: repository, https://github.com/DestinE-Climate-DT/AQUA/
Project-URL: issues, https://github.com/DestinE-Climate-DT/AQUA/issues/
Keywords: climate,modeling,diagnostics,high-resolution
Classifier: Intended Audience :: Developers
Classifier: Intended Audience :: System Administrators
Classifier: Intended Audience :: Science/Research
Classifier: Operating System :: POSIX :: Linux
Classifier: License :: OSI Approved :: Apache Software License
Classifier: Programming Language :: Python
Classifier: Programming Language :: Python :: 3.10
Classifier: Programming Language :: Python :: 3.11
Classifier: Programming Language :: Python :: 3.12
Classifier: Programming Language :: Python :: 3 :: Only
Classifier: Programming Language :: Python :: Implementation :: CPython
Requires-Python: >=3.10
License-File: LICENSE
Requires-Dist: boto3
Requires-Dist: cartopy==0.24.1
Requires-Dist: cfgrib
Requires-Dist: dask[distributed]
Requires-Dist: eccodes==2.41.0
Requires-Dist: filelock
Requires-Dist: gcsfs
Requires-Dist: pandas
Requires-Dist: intake==0.7.0
Requires-Dist: intake-xarray
Requires-Dist: jinja2
Requires-Dist: matplotlib
Requires-Dist: metpy
Requires-Dist: numpy
Requires-Dist: pydantic<2.13.0
Requires-Dist: pypdf
Requires-Dist: pyYAML
Requires-Dist: regionmask
Requires-Dist: ruamel.yaml
Requires-Dist: scipy
Requires-Dist: seaborn
Requires-Dist: smmregrid==0.1.3
Requires-Dist: typeguard
Requires-Dist: xarray<2025.09.1,>=2025.01.2
Requires-Dist: kerchunk
Requires-Dist: h5py>=3.12.1
Requires-Dist: fastparquet
Requires-Dist: pyfdb==0.1.2
Requires-Dist: gsv-interface==2.13.1
Requires-Dist: zarr
Provides-Extra: docs
Requires-Dist: sphinx; extra == "docs"
Requires-Dist: sphinx-rtd-theme; extra == "docs"
Provides-Extra: notebooks
Requires-Dist: ipykernel; extra == "notebooks"
Requires-Dist: healpy; extra == "notebooks"
Provides-Extra: tests
Requires-Dist: pytest; extra == "tests"
Requires-Dist: pytest-cov; extra == "tests"
Requires-Dist: pytest-xdist; extra == "tests"
Requires-Dist: coverage; extra == "tests"
Requires-Dist: cdo; extra == "tests"
Provides-Extra: all
Requires-Dist: aqua-core[docs]; extra == "all"
Requires-Dist: aqua-core[notebooks]; extra == "all"
Requires-Dist: aqua-core[tests]; extra == "all"
Dynamic: license-file
